uromyces/__init__.py
uromyces/_cli.py
uromyces/_compare.py
uromyces/_compat.py
uromyces/_convert.py
uromyces/_plugins.py
uromyces/_types.py
uromyces/_uromyces.abi3.so
uromyces/_uromyces.pyi
uromyces/_util.py
uromyces/py.typed
uromyces-0.0.3.dist-info/METADATA
uromyces-0.0.3.dist-info/WHEEL
uromyces-0.0.3.dist-info/entry_points.txt
uromyces-0.0.3.dist-info/RECORD
