Metadata-Version: 2.4
Name: uromyces
Version: 0.0.3
Classifier: Development Status :: 3 - Alpha
Classifier: Intended Audience :: Education
Classifier: Intended Audience :: End Users/Desktop
Classifier: Intended Audience :: Financial and Insurance Industry
Classifier: Intended Audience :: Information Technology
Classifier: Programming Language :: Rust
Classifier: Programming Language :: Python :: Implementation :: CPython
Classifier: Programming Language :: Python :: Implementation :: PyPy
Classifier: Topic :: Office/Business :: Financial :: Accounting
Classifier: Topic :: Office/Business :: Financial :: Investment
Requires-Dist: click>=7,<9
Requires-Dist: beancount>=3
Requires-Dist: fava>=1.30 ; extra == 'fava'
Provides-Extra: fava
Summary: uromyces implements parts of Beancount's plain text accounting functionality in Rust
Author-email: Jakob Schnitzer <mail@jakobschnitzer.de>
License-Expression: GPL-2.0-only
Requires-Python: >=3.10
Project-URL: Issues, https://github.com/yagebu/uromyces/issues/
Project-URL: Source, https://github.com/yagebu/uromyces/
